{
  "carrot_on_plate": {
    "keywords": [
      "carrot",
      "plate"
    ],
    "excludes": [
      "take carrot off"
    ],
    "n_tasks": 1,
    "n_episodes": 332,
    "total_frames": 10227,
    "task_indices": [
      184
    ],
    "task_strings": [
      "put carrot on plate"
    ],
    "episode_indices": [
      306,
      346,
      784,
      851,
      1030,
      1085,
      1087,
      1088,
      1303,
      1752,
      2033,
      2110,
      2625,
      2963,
      3219,
      3273,
      3678,
      3793,
      3834,
      3898,
      3995,
      3996,
      4202,
      4564,
      4585,
      4631,
      4776,
      4865,
      5127,
      5178,
      5292,
      5353,
      5405,
      5432,
      5584,
      5700,
      5856,
      5857,
      5971,
      6623,
      6675,
      6769,
      6788,
      7083,
      7099,
      7292,
      7428,
      8054,
      8248,
      8867,
      8950,
      9024,
      9291,
      9363,
      9476,
      9538,
      9848,
      9852,
      9859,
      9988,
      10006,
      10878,
      10903,
      12119,
      12239,
      12526,
      12641,
      12874,
      12904,
      13501,
      13667,
      13787,
      14087,
      14091,
      14370,
      14683,
      15067,
      15112,
      15156,
      15296,
      15384,
      15560,
      15758,
      15778,
      15879,
      15919,
      15936,
      15968,
      16062,
      16077,
      16218,
      16315,
      16330,
      16358,
      16568,
      16599,
      16874,
      17065,
      17243,
      17651,
      17976,
      18016,
      18220,
      18532,
      18776,
      18850,
      18921,
      19044,
      19157,
      19168,
      19452,
      19625,
      19733,
      19819,
      19886,
      20136,
      20425,
      20613,
      20660,
      20939,
      21093,
      21155,
      21318,
      21622,
      21761,
      21910,
      22066,
      22091,
      22418,
      22591,
      22661,
      22780,
      22937,
      22946,
      22954,
      23163,
      23200,
      23210,
      23920,
      24003,
      24183,
      24625,
      24660,
      24699,
      24888,
      24969,
      25119,
      25149,
      25263,
      25442,
      25659,
      25670,
      26087,
      26090,
      26379,
      26461,
      26727,
      26794,
      26846,
      27123,
      27152,
      27176,
      27404,
      27657,
      27708,
      27783,
      27909,
      28373,
      28771,
      28876,
      28971,
      29014,
      29180,
      29246,
      29332,
      29355,
      29420,
      29458,
      29522,
      29528,
      29567,
      29761,
      29961,
      29972,
      29980,
      30181,
      30597,
      30672,
      30708,
      30731,
      31204,
      31255,
      31281,
      31300,
      31314,
      31369,
      31559,
      31586,
      31610,
      31894,
      32180,
      32551,
      32590,
      33075,
      33132,
      33297,
      33500,
      33516,
      33669,
      34182,
      34233,
      34396,
      34537,
      34734,
      34815,
      34854,
      35124,
      35300,
      35303,
      35579,
      35625,
      35657,
      35801,
      36156,
      36186,
      36324,
      36341,
      36444,
      36516,
      36535,
      36586,
      36587,
      36710,
      36802,
      36915,
      37155,
      37316,
      37737,
      37848,
      37903,
      38009,
      38230,
      38279,
      38594,
      38638,
      38829,
      39264,
      39366,
      39379,
      39707,
      39736,
      39899,
      39923,
      40022,
      40155,
      40264,
      40346,
      40371,
      40418,
      40543,
      41154,
      41283,
      41400,
      41522,
      41601,
      41634,
      41783,
      41865,
      41975,
      42025,
      42255,
      42401,
      42577,
      42611,
      42742,
      42906,
      43261,
      43735,
      43876,
      44099,
      44197,
      44407,
      44554,
      44827,
      45398,
      45509,
      45754,
      45783,
      45949,
      46020,
      46250,
      46426,
      46901,
      46943,
      47384,
      47435,
      47555,
      47890,
      47911,
      48060,
      48245,
      48306,
      48459,
      48887,
      48895,
      49100,
      49376,
      49533,
      49613,
      49875,
      49934,
      49958,
      50253,
      50310,
      50362,
      50526,
      50565,
      50859,
      50999,
      51039,
      51354,
      51601,
      51791,
      51984,
      51986,
      52157,
      52329,
      52357,
      52514,
      52771,
      52956,
      53024
    ]
  },
  "_skip_eggplant": {
    "keywords": [
      "__never_match_xyz_qq__"
    ],
    "excludes": [
      "take carrot off"
    ],
    "n_tasks": 0,
    "n_episodes": 0,
    "total_frames": 0,
    "task_indices": [],
    "task_strings": [],
    "episode_indices": []
  }
}